drf_complete_autocomplete/__init__.py
drf_complete_autocomplete/configuration.py
drf_complete_autocomplete/filters.py
drf_complete_autocomplete/serializers.py
drf_complete_autocomplete/views.py
drf_complete_autocomplete/widgets.py
drf_complete_autocomplete-1.0.0.dist-info/LICENSE
drf_complete_autocomplete-1.0.0.dist-info/METADATA
drf_complete_autocomplete-1.0.0.dist-info/WHEEL
drf_complete_autocomplete-1.0.0.dist-info/top_level.txt
drf_complete_autocomplete-1.0.0.dist-info/RECORD
