Metadata-Version: 2.1
Name: drf-complete-autocomplete
Version: 1.0.0
Summary: A package supplying tools for easy creating autocompletes with drf.
Author: IIIT
Author-email: github@iiit.pl
License: UNKNOWN
Platform: UNKNOWN
Classifier: Environment :: Web Environment
Classifier: Framework :: Django
Classifier: Intended Audience :: Developers
Classifier: Operating System :: OS Independent
Classifier: Programming Language :: Python
Classifier: Programming Language :: Python :: 3.6
Classifier: Programming Language :: Python :: 3.7
Classifier: Programming Language :: Python :: 3.8
Classifier: Programming Language :: Python :: 3.9
License-File: LICENSE
Requires-Dist: Django (<2.3,>=2.0)
Requires-Dist: djangorestframework (>=3.7.4)
Requires-Dist: six (>=1.9.0)
Provides-Extra: django-filter
Requires-Dist: django-filter ; extra == 'django-filter'
